[
  {
    "datetime": "3/23/2026 2:09:39 AM",
    "incident": "2026076483",
    "agency": "Columbia Police Department",
    "location_txt": "RANGE LINE ST/BLUE RIDGE RD",
    "type": "TRAFFIC STOP",
    "service": "PD",
    "lat": 38.9827458,
    "lon": -92.3260014,
    "generated_at": "2026-03-23 13:14:06 UTC",
    "dispatch_date": "2026-03-23"
  },
  {
    "datetime": "3/23/2026 2:06:22 AM",
    "incident": "2026076482",
    "agency": "Columbia Police Department",
    "location_txt": "3400 BLOCK  SQUIRREL DR",
    "type": "DISTURBANCE",
    "service": "PD",
    "lat": 38.986703,
    "lon": -92.336493,
    "generated_at": "2026-03-23 13:14:06 UTC",
    "dispatch_date": "2026-03-23"
  },
  {
    "datetime": "3/23/2026 1:33:54 AM",
    "incident": "2026076473",
    "agency": "Columbia Police Department",
    "location_txt": "3100 BLOCK  I70 DR SE",
    "type": "911 CHECKS",
    "service": "PD",
    "lat": 38.960237476054,
    "lon": -92.291224305619,
    "generated_at": "2026-03-23 13:14:06 UTC",
    "dispatch_date": "2026-03-23"
  },
  {
    "datetime": "3/23/2026 1:28:01 AM",
    "incident": "2026076472",
    "agency": "Columbia Police Department",
    "location_txt": "W NIFONG BLVD/WILLOWCREEK LN",
    "type": "TRAFFIC STOP",
    "service": "PD",
    "lat": 38.9090641,
    "lon": -92.3597881,
    "generated_at": "2026-03-23 13:14:06 UTC",
    "dispatch_date": "2026-03-23"
  },
  {
    "datetime": "3/23/2026 1:23:37 AM",
    "incident": "2026076471",
    "agency": "Columbia Police Department",
    "location_txt": "300 BLOCK  MAPLEWOOD DR",
    "type": "SUSPICIOUS INCIDENT",
    "service": "PD",
    "lat": 38.9492874,
    "lon": -92.3617075,
    "generated_at": "2026-03-23 13:14:06 UTC",
    "dispatch_date": "2026-03-23"
  },
  {
    "datetime": "3/23/2026 1:22:46 AM",
    "incident": "2026076470",
    "agency": "Columbia Police Department",
    "location_txt": "FORUM BLVD/W SOUTHAMPTON DR",
    "type": "TRAFFIC STOP",
    "service": "PD",
    "lat": 38.9012695,
    "lon": -92.3558154,
    "generated_at": "2026-03-23 13:14:06 UTC",
    "dispatch_date": "2026-03-23"
  },
  {
    "datetime": "3/23/2026 1:09:07 AM",
    "incident": "2026076461",
    "agency": "Columbia Police Department",
    "location_txt": "1400 BLOCK  RANGE LINE ST",
    "type": "DISTURBANCE",
    "service": "PD",
    "lat": 38.965161,
    "lon": -92.324579,
    "generated_at": "2026-03-23 13:14:06 UTC",
    "dispatch_date": "2026-03-23"
  },
  {
    "datetime": "3/23/2026 1:07:06 AM",
    "incident": "2026076460",
    "agency": "Columbia Police Department",
    "location_txt": "4400 BLOCK  BROWN STATION RD",
    "type": "911 CHECKS",
    "service": "PD",
    "lat": 38.995007,
    "lon": -92.28933,
    "generated_at": "2026-03-23 13:14:06 UTC",
    "dispatch_date": "2026-03-23"
  },
  {
    "datetime": "3/23/2026 12:56:32 AM",
    "incident": "2026076455",
    "agency": "Columbia Police Department",
    "location_txt": "4000 BLOCK  HYDE PARK AVE",
    "type": "SUSPICIOUS INCIDENT",
    "service": "PD",
    "lat": 38.906093,
    "lon": -92.329345,
    "generated_at": "2026-03-23 13:14:06 UTC",
    "dispatch_date": "2026-03-23"
  },
  {
    "datetime": "3/23/2026 12:56:29 AM",
    "incident": "2026076454",
    "agency": "Columbia Police Department",
    "location_txt": "GRINDSTONE PKWY/ROCK QUARRY RD",
    "type": "TRAFFIC STOP",
    "service": "PD",
    "lat": 38.9133765,
    "lon": -92.3133936,
    "generated_at": "2026-03-23 13:14:06 UTC",
    "dispatch_date": "2026-03-23"
  },
  {
    "datetime": "3/23/2026 12:50:31 AM",
    "incident": "2026076450",
    "agency": "Columbia Police Department",
    "location_txt": "BUTTONWOOD DR/E NIFONG BLVD",
    "type": "TRAFFIC STOP",
    "service": "PD",
    "lat": 38.9098014,
    "lon": -92.3305456,
    "generated_at": "2026-03-23 13:14:06 UTC",
    "dispatch_date": "2026-03-23"
  },
  {
    "datetime": "3/23/2026 12:49:20 AM",
    "incident": "2026076448",
    "agency": "Columbia Police Department",
    "location_txt": "2500 BLOCK  S PROVIDENCE RD",
    "type": "SUSPICIOUS VEHICLE",
    "service": "PD",
    "lat": 38.9226025,
    "lon": -92.3368845,
    "generated_at": "2026-03-23 13:14:06 UTC",
    "dispatch_date": "2026-03-23"
  },
  {
    "datetime": "3/23/2026 12:41:42 AM",
    "incident": "2026076443",
    "agency": "Columbia Police Department",
    "location_txt": "2000 BLOCK  BLK GRINDSTONE PKWY",
    "type": "TRAFFIC OBSERVATION",
    "service": "PD",
    "lat": 38.913468437487,
    "lon": -92.30901944084,
    "generated_at": "2026-03-23 13:14:06 UTC",
    "dispatch_date": "2026-03-23"
  },
  {
    "datetime": "3/23/2026 12:21:20 AM",
    "incident": "2026076429",
    "agency": "Columbia Police Department",
    "location_txt": "2100 BLOCK  WHISPERING MEADOWS CT",
    "type": "911 CHECKS",
    "service": "PD",
    "lat": 38.9725224,
    "lon": -92.2663648,
    "generated_at": "2026-03-23 13:14:06 UTC",
    "dispatch_date": "2026-03-23"
  },
  {
    "datetime": "3/23/2026 7:30:40 AM",
    "incident": "2026076573",
    "agency": "CFD",
    "location_txt": "3501 NEW HAVEN RD",
    "type": "Vehicle Fire",
    "service": "FIRE_EMS",
    "lat": 38.912558,
    "lon": -92.28534,
    "generated_at": "2026-03-23 13:14:06 UTC",
    "dispatch_date": "2026-03-23"
  },
  {
    "datetime": "3/23/2026 5:50:51 AM",
    "incident": "2026076539",
    "agency": "CFD",
    "location_txt": "1412 RANGE LINE ST",
    "type": "Medical Response",
    "service": "FIRE_EMS",
    "lat": 38.9652951,
    "lon": -92.3245737,
    "generated_at": "2026-03-23 13:14:06 UTC",
    "dispatch_date": "2026-03-23"
  },
  {
    "datetime": "3/23/2026 5:35:56 AM",
    "incident": "2026076536",
    "agency": "CFD",
    "location_txt": "600 RED FEATHER CT",
    "type": "Fire Alarm",
    "service": "FIRE_EMS",
    "lat": 38.951055392773,
    "lon": -92.412693353188,
    "generated_at": "2026-03-23 13:14:06 UTC",
    "dispatch_date": "2026-03-23"
  },
  {
    "datetime": "3/23/2026 3:02:12 AM",
    "incident": "2026076505",
    "agency": "CFD",
    "location_txt": "1 S KEENE ST",
    "type": "Fire Alarm",
    "service": "FIRE_EMS",
    "lat": 38.9478897,
    "lon": -92.2920251,
    "generated_at": "2026-03-23 13:14:06 UTC",
    "dispatch_date": "2026-03-23"
  },
  {
    "datetime": "3/23/2026 2:42:54 AM",
    "incident": "2026076501",
    "agency": "CFD",
    "location_txt": "3850-301 BETHEL ST",
    "type": "Medical Response",
    "service": "FIRE_EMS",
    "lat": 38.9043487,
    "lon": -92.3448964,
    "generated_at": "2026-03-23 13:14:06 UTC",
    "dispatch_date": "2026-03-23"
  },
  {
    "datetime": "3/23/2026 1:35:49 AM",
    "incident": "2026076474",
    "agency": "BCFD",
    "location_txt": "6183-4 N WEST WILCOTT ST",
    "type": "Smoke Alarm",
    "service": "FIRE_EMS",
    "lat": 39.020172227261,
    "lon": -92.325392432082,
    "generated_at": "2026-03-23 13:14:06 UTC",
    "dispatch_date": "2026-03-23"
  }
]